{
    "jobs":[
        {
            "id":1,
            "name":"Software Developer",
            "salary":"4 LPA",
            "location":"Hyderabad"
        },
        {
            "id":2,
            "name":"Servicenow Developer",
            "salary":"8 LPA",
            "location":"Hyderabad Town"
        },
        {
            "id":3,
            "name":"Frontend Developer",
            "salary":"12 LPA",
            "location":"Banglore"
        },
        {
            "id":4,
            "name":"Backend Developer",
            "salary":"16 LPA",
            "location":"Chennai"
        },
        {
            "id":5,
            "name":"GoLang Developer",
            "salary":"10 LPA",
            "location":"Work From Home"
        }
    ]
}